README.md
setup.py
timeing/__init__.py
timeing/timeing.py
timeing.egg-info/PKG-INFO
timeing.egg-info/SOURCES.txt
timeing.egg-info/dependency_links.txt
timeing.egg-info/top_level.txt