Metadata-Version: 2.1
Name: timeing
Version: 0.1
Summary: 定时运行程序库
Home-page: https://www.kuko.icu/
Author: PYmili
Author-email: 2097632843@qq.com
Maintainer: PYmili
Maintainer-email: 2097632843@qq.com
License: MIT License
Platform: UNKNOWN
Classifier: Development Status :: 3 - Alpha
Classifier: Intended Audience :: Developers
Classifier: Topic :: Software Development :: Build Tools
Classifier: License :: OSI Approved :: MIT License
Classifier: Programming Language :: Python :: 3.9
Requires-Python: >=3.9
